jupyterlab_wipp/__init__.py
jupyterlab_wipp/_version.py
jupyterlab_wipp/handlers.py
jupyterlab_wipp/wipp.py
jupyterlab_wipp/labextension/build_log.json
jupyterlab_wipp/labextension/package.json
jupyterlab_wipp/labextension/schemas/jupyterlab_wipp/package.json.orig
jupyterlab_wipp/labextension/schemas/jupyterlab_wipp/plugin.json
jupyterlab_wipp/labextension/static/7ada1c88f72f05e9b5cb43436e3638e6.svg
jupyterlab_wipp/labextension/static/lib_index_js.bec80ddcb75e3fa21a51.js
jupyterlab_wipp/labextension/static/lib_index_js.bec80ddcb75e3fa21a51.js.map
jupyterlab_wipp/labextension/static/remoteEntry.7b161ae1d5f52343515d.js
jupyterlab_wipp/labextension/static/remoteEntry.7b161ae1d5f52343515d.js.map
jupyterlab_wipp/labextension/static/style.js
jupyterlab_wipp/labextension/static/style_index_js.5d726f3250aca89623c8.js
jupyterlab_wipp/labextension/static/style_index_js.5d726f3250aca89623c8.js.map
jupyterlab_wipp/labextension/static/vendors-node_modules_css-loader_dist_runtime_api_js-node_modules_css-loader_dist_runtime_cssW-313cda.d2abe8c6a5bfd74145d1.js
jupyterlab_wipp/labextension/static/vendors-node_modules_css-loader_dist_runtime_api_js-node_modules_css-loader_dist_runtime_cssW-313cda.d2abe8c6a5bfd74145d1.js.map
jupyterlab_wipp-1.2.0.data/data/etc/jupyter/jupyter_notebook_config.d/jupyterlab_wipp.json
jupyterlab_wipp-1.2.0.data/data/etc/jupyter/jupyter_server_config.d/jupyterlab_wipp.json
jupyterlab_wipp-1.2.0.data/data/share/jupyter/labextensions/jupyterlab_wipp/build_log.json
jupyterlab_wipp-1.2.0.data/data/share/jupyter/labextensions/jupyterlab_wipp/install.json
jupyterlab_wipp-1.2.0.data/data/share/jupyter/labextensions/jupyterlab_wipp/package.json
jupyterlab_wipp-1.2.0.data/data/share/jupyter/labextensions/jupyterlab_wipp/schemas/jupyterlab_wipp/package.json.orig
jupyterlab_wipp-1.2.0.data/data/share/jupyter/labextensions/jupyterlab_wipp/schemas/jupyterlab_wipp/plugin.json
jupyterlab_wipp-1.2.0.dist-info/LICENSE
jupyterlab_wipp-1.2.0.dist-info/METADATA
jupyterlab_wipp-1.2.0.dist-info/WHEEL
jupyterlab_wipp-1.2.0.dist-info/top_level.txt
jupyterlab_wipp-1.2.0.dist-info/RECORD
