Metadata-Version: 2.1
Name: jupyterlab-wipp
Version: 1.2.0
Summary: WIPP integration with JupyterLab
Home-page: https://github.com/labshare/jupyterlab-extensions.git
Author: Konstantin Taletskiy
Author-email: konstantin.taletskiy@labshare.org
License: MIT
Keywords: Jupyter,JupyterLab,JupyterLab3
Platform: Linux
Platform: Mac OS X
Platform: Windows
Classifier: License :: OSI Approved :: BSD License
Classifier: Programming Language :: Python
Classifier: Programming Language :: Python :: 3
Classifier: Programming Language :: Python :: 3.6
Classifier: Programming Language :: Python :: 3.7
Classifier: Programming Language :: Python :: 3.8
Classifier: Programming Language :: Python :: 3.9
Classifier: Framework :: Jupyter
Requires-Python: >=3.6
Requires-Dist: jupyter-server (<2,>=1.6)
